dotfile_manager_aquanjsw/__init__.py
dotfile_manager_aquanjsw/helper.py
dotfile_manager_aquanjsw/logging_.py
dotfile_manager_aquanjsw/main.py
dotfile_manager_aquanjsw/model.py
dotfile_manager_aquanjsw/argparser_/__init__.py
dotfile_manager_aquanjsw/argparser_/root_parser.py
dotfile_manager_aquanjsw/argparser_/subparser/__init__.py
dotfile_manager_aquanjsw/argparser_/subparser/query_parser.py
dotfile_manager_aquanjsw/argparser_/subparser/register_parser.py
dotfile_manager_aquanjsw/argparser_/subparser/sync_parser.py
dotfile_manager_aquanjsw-0.1.3.dist-info/METADATA
dotfile_manager_aquanjsw-0.1.3.dist-info/WHEEL
dotfile_manager_aquanjsw-0.1.3.dist-info/entry_points.txt
dotfile_manager_aquanjsw-0.1.3.dist-info/RECORD
