Metadata-Version: 2.3
Name: dotfile_manager_aquanjsw
Version: 0.1.3
Summary: Help manage your dotfiles
Project-URL: Homepage, https://github.com/aquanjsw/dotfile-manager
Author-email: aquanjsw <zhdlcc@gmail.com>
Classifier: Operating System :: OS Independent
Classifier: Programming Language :: Python :: 3
Requires-Python: >=3.8
Requires-Dist: appdirs
Requires-Dist: pyyaml
Requires-Dist: sqlmodel
Requires-Dist: tabulate
